shortable/__init__.py
shortable/shortable.py
tests/__init__.py
tests/test_shortable.py
shortable-0.1.0.dist-info/LICENSE.txt
shortable-0.1.0.dist-info/METADATA
shortable-0.1.0.dist-info/WHEEL
shortable-0.1.0.dist-info/entry_points.txt
shortable-0.1.0.dist-info/top_level.txt
shortable-0.1.0.dist-info/RECORD
