Metadata-Version: 2.1
Name: shortable
Version: 0.1.0
Summary: Receive an alert if an asset becomes shortable, e.g. from HTB to ETB, or vice versa
Home-page: https://github.com/rgomezjnr/shortable
Author: Robert Gomez, Jr.
Author-email: rgomezjnr@gmail.com
License: MIT
Keywords: assets stocks short sell stock market trade broker alpaca windows toast notification alert database json api cli tool script python
Platform: UNKNOWN
Classifier: Programming Language :: Python :: 3
Classifier: Programming Language :: Python :: 3.6
Classifier: Programming Language :: Python :: 3.7
Classifier: Programming Language :: Python :: 3.8
Classifier: Programming Language :: Python :: 3.9
Classifier: License :: OSI Approved :: MIT License
Classifier: Operating System :: Microsoft :: Windows :: Windows 10
Classifier: Development Status :: 3 - Alpha
Classifier: Environment :: Console
Classifier: Intended Audience :: End Users/Desktop
Classifier: Intended Audience :: Financial and Insurance Industry
Classifier: Topic :: Database
Classifier: Topic :: Desktop Environment
Classifier: Topic :: Internet
Classifier: Topic :: Office/Business :: Financial
Classifier: Topic :: Office/Business :: Financial :: Investment
Classifier: Topic :: Utilities
Requires-Python: >=3.6
Requires-Dist: winotify
Requires-Dist: alpaca-trade-api
